{
  "configuraciones": {
    "app": {
      "version": "1.2.3-beta",
      "nombre": "CheckIt"
    },
    "topNavbar": {
      "colorFondo": "#dc3545",
      "logoImagen": "sanbornsWhite.svg",
      "scrollPixeles": 5,
      "animacionMs": 300,
      "alturaNavbar": 60,
      "mostrarHamburger": true
    }
  },
  "mesas": [
    {
      "id": 201,
      "numero": 201,
      "estado": "ocupada",
      "mesero": "JOSE LUIS BAENA LOPEZ",
      "personas": 2,
      "adultos": 2,
      "ninos": 0,
      "cuentaAbierta": true,
      "subtotal": 580.0,
      "impuestos": 92.8,
      "total": 672.8,
      "propina": 0,
      "totalConPropina": 672.8,
      "timestamp": "2025-07-02T10:47:00Z",
      "orden": null
    }
  ],
  "ordenes": [
    {
      "id": 1,
      "mesaId": 201,
      "items": [],
      "subtotal": 0,
      "impuestos": 0,
      "total": 0,
      "estado": "pendiente",
      "timestamp": "2025-07-02T10:47:00Z"
    }
  ],
  "estados": [
    {
      "id": "pendiente",
      "nombre": "Pendiente",
      "descripcion": "Orden creada, esperando confirmación"
    },
    {
      "id": "enviada",
      "nombre": "Enviada a Cocina",
      "descripcion": "Orden confirmada y enviada a cocina"
    },
    {
      "id": "preparando",
      "nombre": "Preparando",
      "descripcion": "Cocinando los platillos"
    },
    {
      "id": "servida",
      "nombre": "Servida",
      "descripcion": "Platillos entregados en la mesa"
    },
    {
      "id": "pagada",
      "nombre": "Pagada",
      "descripcion": "Cuenta pagada, mesa libre"
    }
  ],
  "promociones": {
    "lstima": [
      "https://images.unsplash.com/photo-1555939594-58d7cb561ad1?w=1080&h=600&fit=crop",
      "https://images.unsplash.com/photo-1517248135467-4c7edcad34c4?w=1080&h=600&fit=crop",
      "https://images.unsplash.com/photo-1414235077428-338989a2e8c0?w=1080&h=600&fit=crop"
    ]
  },
  "consultacuenta": {
    "Codigo": 0,
    "Descripcion": "cuenta",
    "Errores": null,
    "Descuento": "0.00",
    "Folio": 0,
    "Impuesto": "65.52",
    "Mesero": 3,
    "Personas": 4,
    "Platillos": [
      {
        "Comensal": "1",
        "Descuento": 0,
        "EsAdicional": 0,
        "EsCombo": 0,
        "cantidad": 1.0,
        "codigo": 1,
        "descripcion": "HUEVOS RANCHEROS",
        "descuentoLinea": 0,
        "impuesto": 1600,
        "linea": 1,
        "precioUnitario": "65.00",
        "valImpuesto": 56.0344827586207
      },
      {
        "Comensal": "2",
        "Descuento": 0,
        "EsAdicional": 0,
        "EsCombo": 0,
        "cantidad": 1.0,
        "codigo": 7,
        "descripcion": "Breakfast Bagel",
        "descuentoLinea": 0,
        "impuesto": 1600,
        "linea": 2,
        "precioUnitario": "280.00",
        "valImpuesto": 241.379310344828
      },
      {
        "Comensal": "3",
        "Descuento": 0,
        "EsAdicional": 0,
        "EsCombo": 0,
        "cantidad": 1.0,
        "codigo": 22,
        "descripcion": "CHILAQUILES ROJOS",
        "descuentoLinea": 0,
        "impuesto": 1600,
        "linea": 3,
        "precioUnitario": "85.00",
        "valImpuesto": 73.2758620689655
      },
      {
        "Comensal": "4",
        "Descuento": 0,
        "EsAdicional": 0,
        "EsCombo": 0,
        "cantidad": 1.0,
        "codigo": 20,
        "descripcion": "ENSALADA DE ATÚN",
        "descuentoLinea": 0,
        "impuesto": 1600,
        "linea": 4,
        "precioUnitario": "45.00",
        "valImpuesto": 38.7931034482759
      }
    ],
    "Subtotal": "475.00",
    "Total": "540.52"
  },
  "nombreMesero": {
    "Codigo": 0,
    "Descripcion": "JOSE LUIS BAENA LOPEZ",
    "Errores": null
  }
}
